fsed/VERSION
fsed/__init__.py
fsed/ahocorasick.py
fsed/compat.py
fsed/fsed.py
fsed/utils.py
fsed/tests/__init__.py
fsed/tests/test_ahocorasick.py
fsed/tests/test_fsed.py
fsed-0.5.4.dist-info/DESCRIPTION.rst
fsed-0.5.4.dist-info/METADATA
fsed-0.5.4.dist-info/RECORD
fsed-0.5.4.dist-info/WHEEL
fsed-0.5.4.dist-info/entry_points.txt
fsed-0.5.4.dist-info/metadata.json
fsed-0.5.4.dist-info/top_level.txt
